CHANGELOG.md
celery_yaml-2.2.0.dist-info/METADATA
celery_yaml-2.2.0.dist-info/WHEEL
celery_yaml-2.2.0.dist-info/entry_points.txt
celery_yaml-2.2.0.dist-info/licenses/LICENSE
celery_yaml/__init__.py
celery_yaml/loader.py
celery_yaml/py.typed
celery_yaml/pyramid.py
celery_yaml-2.2.0.dist-info/RECORD
