Metadata-Version: 2.1
Name: celery-yaml
Version: 2.2.0
Summary: Easy configuration for celery app using Yaml file
Author-Email: Guillaume Gauvrit <guillaume@gauvr.it>
License: BSD
Project-URL: Homepage, https://github.com/mardiros/celery-yaml
Project-URL: Documentation, https://github.com/mardiros/celery-yaml/blob/main/README.md
Project-URL: Repository, https://github.com/mardiros/celery-yaml.git
Project-URL: Issues, https://github.com/mardiros/celery-yaml/issues
Project-URL: Changelog, https://github.com/mardiros/celery-yaml/blob/main/CHANGELOG.md
Requires-Python: >=3.9
Requires-Dist: celery<6,>=5.4.0
Requires-Dist: pyyaml<7,>=6.0.0
Requires-Dist: envsub<1,>=0.1.15
